{
    "fluentMethods": true,
    "relationships": [],
    "fields": [
        {
            "fieldName": "insertDate",
            "fieldType": "LocalDate"
        },
        {
            "fieldName": "fileDate",
            "fieldType": "LocalDate"
        },
        {
            "fieldName": "module",
            "fieldType": "String"
        },
        {
            "fieldName": "ruleGroupId",
            "fieldType": "Long"
        },
        {
            "fieldName": "ruleId",
            "fieldType": "Long"
        },
        {
            "fieldName": "viewId",
            "fieldType": "Long"
        },
        {
            "fieldName": "type",
            "fieldType": "String"
        },
        {
            "fieldName": "dvCount",
            "fieldType": "BigDecimal"
        },
        {
            "fieldName": "typeCount",
            "fieldType": "BigDecimal"
        },
        {
            "fieldName": "createdBy",
            "fieldType": "Long"
        },
        {
            "fieldName": "createdDate",
            "fieldType": "ZonedDateTime"
        },
        {
            "fieldName": "lastUpdatedBy",
            "fieldType": "Long"
        },
        {
            "fieldName": "lastUpdatedDate",
            "fieldType": "ZonedDateTime"
        }
    ],
    "changelogDate": "20180130054928",
    "dto": "no",
    "service": "no",
    "entityTableName": "app_module_summary",
    "pagination": "pager",
    "microserviceName": "agreeApplication"
}
